<?xml version="1.0" encoding="utf-8"?>
<typeSystemDescription xmlns="http://uima.apache.org/resourceSpecifier">
  <name>Lakes in Argentina Uruguay Paraguay Bolivia Brazil-ts</name>
  <description>Lakes in Argentina Uruguay Paraguay Bolivia Brazil</description>
  <version></version>
  <vendor></vendor>
  <types>
    <typeDescription>
      <name>com.menRISA.Lakes_in_Argentina_Uruguay_Paraguay_Bolivia_Brazil</name>
      <description>Lakes in Argentina Uruguay Paraguay Bolivia Brazil</description>
      <supertypeName>uima.tt.DictionaryEntryAnnotation</supertypeName>
    </typeDescription>
    </types>
</typeSystemDescription>
